import_profiler.py
import_profiler-0.0.3.dist-info/DESCRIPTION.rst
import_profiler-0.0.3.dist-info/METADATA
import_profiler-0.0.3.dist-info/metadata.json
import_profiler-0.0.3.dist-info/RECORD
import_profiler-0.0.3.dist-info/top_level.txt
import_profiler-0.0.3.dist-info/WHEEL
