Metadata-Version: 2.0
Name: import-profiler
Version: 0.0.3
Summary: Import profiler to find bottlenecks in import times.
Home-page: UNKNOWN
Author: David Cournapeau
Author-email: cournape@gmail.com
License: MIT
Platform: UNKNOWN
Requires-Dist: tabulate (>=0.7.5)
